ab_core/impersonation/__init__.py
ab_core/impersonation/impersonator/__init__.py
ab_core/impersonation/impersonator/base.py
ab_core/impersonation/impersonator/template.py
ab_core/impersonation/impersonator/playwright/__init__.py
ab_core/impersonation/impersonator/playwright/base.py
ab_core/impersonation/impersonator/playwright/browserless.py
ab_core/impersonation/impersonator/playwright/cdp.py
ab_core/impersonation/impersonator/playwright/standard.py
ab_core/impersonation/schema/__init__.py
ab_core/impersonation/schema/impersonation_exchange.py
ab_core/impersonation/schema/impersonation_tool.py
ab_core/impersonation/schema/intercept_event.py
ab_impersonation-0.2.1.dist-info/METADATA
ab_impersonation-0.2.1.dist-info/WHEEL
ab_impersonation-0.2.1.dist-info/licenses/LICENSE
ab_impersonation-0.2.1.dist-info/RECORD
