Metadata-Version: 2.4
Name: ab-impersonation
Version: 0.2.1
Author-email: Matthew Coulter <53892067+mattcoulter7@users.noreply.github.com>
License-File: LICENSE
Requires-Python: <4,>=3.12
Requires-Dist: httpx>=0.28.1
Requires-Dist: playwright<2,>=1.52.0
Requires-Dist: pydantic<3,>=2.11.7
Requires-Dist: requests>=2.32.5
Requires-Dist: uuid7<0.2,>=0.1.0
